{
  "posts": [
    {
      "_id": "5c74d15fb5b8622d5865e38a",
      "index": 0,
      "guid": "cfff4387-2df6-4e73-a0f7-febefa6044e5",
      "isActive": true,
      "balance": "$3,457.17",
      "picture": "http://placehold.it/32x32",
      "age": 28,
      "eyeColor": "brown",
      "name": {
        "first": "Beryl",
        "last": "Richmond"
      },
      "company": "APPLIDEC",
      "email": "beryl.richmond@applidec.biz",
      "phone": "+1 (972) 457-3000",
      "address": "226 Ellery Street, Thermal, Virgin Islands, 5587",
      "title": "ullamco cillum cillum voluptate nostrud",
      "body": "Nisi velit elit Lorem magna esse aute esse veniam sint amet exercitation consequat aliqua. Consequat eiusmod sunt irure non laboris excepteur aliqua mollit non sint duis laboris qui. Officia cupidatat consectetur ut voluptate minim irure culpa in nulla aute aute amet cupidatat dolore. Ut culpa tempor ullamco cillum minim adipisicing.",
      "registered": "Tuesday, December 15, 2015 12:36 PM",
      "latitude": "78.273203",
      "longitude": "123.72926",
      "tags": [
        "qui",
        "pariatur",
        "culpa",
        "pariatur",
        "reprehenderit"
      ],
      "range": [
        0,
        1,
        2,
        3,
        4,
        5,
        6,
        7,
        8,
        9
      ],
      "friends": [
        {
          "id": 0,
          "name": "Beth Ball"
        },
        {
          "id": 1,
          "name": "Russell Harrington"
        },
        {
          "id": 2,
          "name": "Haley Atkinson"
        }
      ],
      "greeting": "Hello, Beryl! You have 9 unread messages.",
      "favoriteFruit": "apple"
    },
    {
      "_id": "5c74d15f624cc35d27e42d68",
      "index": 1,
      "guid": "7abce745-cb10-45f4-b2b3-419aa53a0016",
      "isActive": true,
      "balance": "$2,712.36",
      "picture": "http://placehold.it/32x32",
      "age": 35,
      "eyeColor": "green",
      "name": {
        "first": "Elaine",
        "last": "Carr"
      },
      "company": "ORBIN",
      "email": "elaine.carr@orbin.net",
      "phone": "+1 (902) 555-2964",
      "address": "508 Eastern Parkway, Yonah, Idaho, 1592",
      "title": "ea magna non deserunt laborum",
      "body": "Cupidatat ea dolor quis nisi in elit voluptate magna incididunt. Deserunt enim fugiat culpa aute exercitation exercitation eu. Do ea sint consectetur duis sit ipsum proident consectetur ullamco Lorem quis. Ea officia ut dolore voluptate est aliqua. Officia aliqua ex et anim excepteur.",
      "registered": "Sunday, November 26, 2017 11:27 PM",
      "latitude": "-48.536932",
      "longitude": "113.249848",
      "tags": [
        "minim",
        "occaecat",
        "consectetur",
        "aliqua",
        "exercitation"
      ],
      "range": [
        0,
        1,
        2,
        3,
        4,
        5,
        6,
        7,
        8,
        9
      ],
      "friends": [
        {
          "id": 0,
          "name": "Mcpherson Mosley"
        },
        {
          "id": 1,
          "name": "Tanya Horn"
        },
        {
          "id": 2,
          "name": "Kayla Duran"
        }
      ],
      "greeting": "Hello, Elaine! You have 5 unread messages.",
      "favoriteFruit": "banana"
    }
  ],
  "projects": [
    {
      "projectId": 1,
      "customerName": "Dereje",
      "address1": "123 Street ABC",
      "address2": "Silver Spring , MD",
      "date": "43059",
      "preparedBy": "DTK",
      "jobNumber": "3010",
      "productionMeter": true
    },
    {
      "projectId": 2,
      "customerName": "Winta",
      "address1": "124 Street ABC",
      "address2": "Silver Spring , MD",
      "date": "43059",
      "preparedBy": "AAA",
      "jobNumber": "3011",
      "productionMeter": true
    },
    {
      "projectId": 3,
      "customerName": "Ruhama",
      "address1": "125 Street ABC",
      "address2": "Silver Spring , MD",
      "date": "43059",
      "preparedBy": "AAA",
      "jobNumber": "3012",
      "productionMeter": true
    }
  ],
  "profile": {
    "name": "typicode"
  }
}
